pyql/__init__.py
pyql/patching.py
pyql/schema/__init__.py
pyql/schema/compile.py
pyql/schema/types/__init__.py
pyql/schema/types/core.py
pyql/schema/types/enum_type.py
pyql/schema/types/extra.py
pyql/utils/__init__.py
pyql/utils/cache.py
pyql/utils/str_converters.py
PyQL-3.0.0.dist-info/METADATA
PyQL-3.0.0.dist-info/WHEEL
PyQL-3.0.0.dist-info/top_level.txt
PyQL-3.0.0.dist-info/RECORD
