Metadata-Version: 2.1
Name: PyQL
Version: 3.0.0
Summary: UNKNOWN
Home-page: https://github.com/rshk/pyql
Author: Samuele Santi
Author-email: samuele.santi@reinventsoftware.io
License: BSD License
Platform: UNKNOWN
Classifier: License :: OSI Approved :: BSD License
Classifier: Programming Language :: Python :: 3 :: Only
Classifier: Programming Language :: Python :: 3.6
Classifier: Programming Language :: Python :: 3.7
Classifier: Programming Language :: Python :: 3.8
Classifier: Programming Language :: Python :: 3.9
Provides-Extra: dev
